{
  "sources": [
    {
      "title": "Hacker News",
      "feedUrl": "https://news.ycombinator.com/rss",
      "siteUrl": "https://news.ycombinator.com/",
      "articles": [
        {
          "id": "https://www.economist.com/europe/2021/06/19/the-eu-made-in-america",
          "author": null,
          "description": "Comments",
          "link": "https://www.economist.com/europe/2021/06/19/the-eu-made-in-america",
          "publishedOn": "2021-06-20T00:06:36.000Z",
          "wordCount": 1197,
          "title": "The EU: Made in America"
        },
        {
          "id": "https://www.renoise.com/",
          "author": null,
          "description": "Comments",
          "link": "https://www.renoise.com/",
          "publishedOn": "2021-06-19T23:11:10.000Z",
          "wordCount": 508,
          "title": "Renoise – a DAW with a tracker-like interface"
        },
        {
          "id": "http://www.koreaherald.com/view.php?ud=20210617000953",
          "author": null,
          "description": "Comments",
          "link": "http://www.koreaherald.com/view.php?ud=20210617000953",
          "publishedOn": "2021-06-19T22:30:24.000Z",
          "wordCount": null,
          "title": "Korea revokes approvals for 1,700 communication equipment, devices"
        },
        {
          "id": "https://9to5mac.com/2021/06/19/a-specific-network-name-can-completely-disable-wi-fi-on-your-iphone/",
          "author": null,
          "description": "Comments",
          "link": "https://9to5mac.com/2021/06/19/a-specific-network-name-can-completely-disable-wi-fi-on-your-iphone/",
          "publishedOn": "2021-06-19T21:34:41.000Z",
          "wordCount": 755,
          "title": "A specific network name can completely disable Wi-Fi on your iPhone"
        },
        {
          "id": "https://www.ycombinator.com/companies/community-phone-company/jobs/6psvnZD-digital-marketing-specialist",
          "author": null,
          "description": "Comments",
          "link": "https://www.ycombinator.com/companies/community-phone-company/jobs/6psvnZD-digital-marketing-specialist",
          "publishedOn": "2021-06-19T21:00:30.000Z",
          "wordCount": 818,
          "title": "Community Phone Company (YC W19) Is Hiring"
        },
        {
          "id": "https://journals.lww.com/americantherapeutics/Abstract/9000/Ivermectin_for_Prevention_and_Treatment_of.98040.aspx",
          "author": null,
          "description": "Comments",
          "link": "https://journals.lww.com/americantherapeutics/Abstract/9000/Ivermectin_for_Prevention_and_Treatment_of.98040.aspx",
          "publishedOn": "2021-06-19T17:26:52.000Z",
          "wordCount": 1916,
          "title": "Ivermectin for Prevention and Treatment of Covid-19 Infection"
        },
        {
          "id": "https://www.reuters.com/article/ctech-us-usa-semiconductors-congress-idCAKCN2DT29F-OCATC",
          "author": null,
          "description": "Comments",
          "link": "https://www.reuters.com/article/ctech-us-usa-semiconductors-congress-idCAKCN2DT29F-OCATC",
          "publishedOn": "2021-06-19T15:20:40.000Z",
          "wordCount": 428,
          "title": "U.S. senators propose 25% tax credit for semiconductor manufacturing"
        },
        {
          "id": "https://news.ycombinator.com/item?id=27560781",
          "author": null,
          "description": "Comments",
          "link": "https://news.ycombinator.com/item?id=27560781",
          "publishedOn": "2021-06-19T14:39:45.000Z",
          "wordCount": 13544,
          "title": "I'm Peter Roberts, immigration attorney who does work for YC startups. AMA"
        },
        {
          "id": "https://greenrobot.org/release/eventbus-3-1-plain-java-support/",
          "author": null,
          "description": "Comments",
          "link": "https://greenrobot.org/release/eventbus-3-1-plain-java-support/",
          "publishedOn": "2021-06-19T14:11:26.000Z",
          "wordCount": 745,
          "title": "EventBus 3.1 with plain Java support"
        },
        {
          "id": "https://www.businessinsider.com/inside-coober-pedy-australias-underground-town-2016-1",
          "author": null,
          "description": "Comments",
          "link": "https://www.businessinsider.com/inside-coober-pedy-australias-underground-town-2016-1",
          "publishedOn": "2021-06-19T14:09:24.000Z",
          "wordCount": 2121,
          "title": "Coober Pedy, the Australian mining town where residents live underground (2020)"
        },
        {
          "id": "http://adamcadre.ac/calendar/202105m.html",
          "author": null,
          "description": "Comments",
          "link": "http://adamcadre.ac/calendar/202105m.html",
          "publishedOn": "2021-06-19T13:49:58.000Z",
          "wordCount": 1767,
          "title": "Life as a public school teacher in the San Francisco Bay Area in 2021"
        },
        {
          "id": "https://people.eecs.berkeley.edu/~pister/publications/2018/BurnettTapeoutClassISCAS2018.pdf",
          "author": null,
          "description": "Comments",
          "link": "https://people.eecs.berkeley.edu/~pister/publications/2018/BurnettTapeoutClassISCAS2018.pdf",
          "publishedOn": "2021-06-19T13:38:50.000Z",
          "wordCount": 23053,
          "title": "Taking students from schematic to silicon in one semester (2018) [pdf]"
        },
        {
          "id": "https://en.wikipedia.org/wiki/Casu_martzu",
          "author": null,
          "description": "Comments",
          "link": "https://en.wikipedia.org/wiki/Casu_martzu",
          "publishedOn": "2021-06-19T13:24:19.000Z",
          "wordCount": 1914,
          "title": "Casu Martzu"
        },
        {
          "id": "https://knowablemagazine.org/article/living-world/2021/evolution-dad",
          "author": null,
          "description": "Comments",
          "link": "https://knowablemagazine.org/article/living-world/2021/evolution-dad",
          "publishedOn": "2021-06-19T12:59:35.000Z",
          "wordCount": 100,
          "title": "Evolution of the Dad"
        },
        {
          "id": "https://www.nature.com/articles/d41586-021-01627-2",
          "author": null,
          "description": "Comments",
          "link": "https://www.nature.com/articles/d41586-021-01627-2",
          "publishedOn": "2021-06-19T12:33:13.000Z",
          "wordCount": 2526,
          "title": "Mathematicians welcome computer-assisted proof in ‘grand unification’ theory"
        },
        {
          "id": "https://morrick.me/archives/9368",
          "author": null,
          "description": "Comments",
          "link": "https://morrick.me/archives/9368",
          "publishedOn": "2021-06-19T12:15:13.000Z",
          "wordCount": 1958,
          "title": "Safari 15 on Mac OS, a user interface mess"
        },
        {
          "id": "https://ij.org/press-release/north-carolina-board-tells-retired-engineer-he-cant-talk-about-engineering/",
          "author": null,
          "description": "Comments",
          "link": "https://ij.org/press-release/north-carolina-board-tells-retired-engineer-he-cant-talk-about-engineering/",
          "publishedOn": "2021-06-19T12:09:37.000Z",
          "wordCount": 1091,
          "title": "North Carolina tells retired engineer he can't talk about engineering"
        },
        {
          "id": "https://robert.ocallahan.org/2021/06/spectre-mitigations-murder-userspace.html",
          "author": null,
          "description": "Comments",
          "link": "https://robert.ocallahan.org/2021/06/spectre-mitigations-murder-userspace.html",
          "publishedOn": "2021-06-19T12:07:27.000Z",
          "wordCount": 908,
          "title": "Spectre mitigations murder userspace performance"
        },
        {
          "id": "https://arstechnica.com/gadgets/2021/06/newly-discovered-vigilante-malware-outs-software-pirates-and-blocks-them/",
          "author": null,
          "description": "Comments",
          "link": "https://arstechnica.com/gadgets/2021/06/newly-discovered-vigilante-malware-outs-software-pirates-and-blocks-them/",
          "publishedOn": "2021-06-19T10:13:34.000Z",
          "wordCount": 1012,
          "title": "Newly discovered Vigilante malware outs software pirates and blocks them"
        },
        {
          "id": "https://www.smithsonianmag.com/history/inside-tombs-saqqara-180977932/",
          "author": null,
          "description": "Comments",
          "link": "https://www.smithsonianmag.com/history/inside-tombs-saqqara-180977932/",
          "publishedOn": "2021-06-19T10:01:05.000Z",
          "wordCount": 4872,
          "title": "Inside The Tombs of Saqqara"
        },
        {
          "id": "https://techcrunch.com/2021/06/17/deep-reinforcement-learning-will-transform-manufacturing-as-we-know-it/",
          "author": null,
          "description": "Comments",
          "link": "https://techcrunch.com/2021/06/17/deep-reinforcement-learning-will-transform-manufacturing-as-we-know-it/",
          "publishedOn": "2021-06-19T04:51:25.000Z",
          "wordCount": 1087,
          "title": "Deep reinforcement learning will transform manufacturing as we know it"
        },
        {
          "id": "https://peewee.com/2021/06/18/rest-in-peace-john-paragon/",
          "author": null,
          "description": "Comments",
          "link": "https://peewee.com/2021/06/18/rest-in-peace-john-paragon/",
          "publishedOn": "2021-06-18T23:46:46.000Z",
          "wordCount": 477,
          "title": "Rest In Peace, John. I was lucky to know you so deeply"
        },
        {
          "id": "https://news.ycombinator.com/item?id=27548204",
          "author": null,
          "description": "Comments",
          "link": "https://news.ycombinator.com/item?id=27548204",
          "publishedOn": "2021-06-18T07:38:29.000Z",
          "wordCount": 7708,
          "title": "Ask HN: What huge mistake did you make early in your career?"
        },
        {
          "id": "https://www.youtube.com/watch?v=AJhx8SeI0Q8",
          "author": null,
          "description": "Comments",
          "link": "https://www.youtube.com/watch?v=AJhx8SeI0Q8",
          "publishedOn": "2021-06-18T06:20:32.000Z",
          "wordCount": 17,
          "title": "MiSTer FPGA GBA Splitscreen Multiplayer"
        },
        {
          "id": "https://www.researchgate.net/publication/319392963_A_Swingogram_Representation_for_Tracking_Micro-Rhythmic_Variation_in_Jazz_Performances",
          "author": null,
          "description": "Comments",
          "link": "https://www.researchgate.net/publication/319392963_A_Swingogram_Representation_for_Tracking_Micro-Rhythmic_Variation_in_Jazz_Performances",
          "publishedOn": "2021-06-17T11:27:06.000Z",
          "wordCount": 15066,
          "title": "Tracking Micro-Rhythmic Variation in Jazz Performances (2017)"
        },
        {
          "id": "https://saagarjha.com/blog/2020/04/12/designing-a-better-strcpy/",
          "author": null,
          "description": "Comments",
          "link": "https://saagarjha.com/blog/2020/04/12/designing-a-better-strcpy/",
          "publishedOn": "2021-06-17T09:50:50.000Z",
          "wordCount": 2288,
          "title": "Designing a better strcpy"
        },
        {
          "id": "https://www.zverovich.net/2021/06/16/safe-formatting-api.html",
          "author": null,
          "description": "Comments",
          "link": "https://www.zverovich.net/2021/06/16/safe-formatting-api.html",
          "publishedOn": "2021-06-17T05:50:57.000Z",
          "wordCount": 1235,
          "title": "A quest for safe text formatting API"
        },
        {
          "id": "https://github.com/laramies/theHarvester",
          "author": null,
          "description": "Comments",
          "link": "https://github.com/laramies/theHarvester",
          "publishedOn": "2021-06-17T05:17:27.000Z",
          "wordCount": 1301,
          "title": "TheHarvester: Emails, subdomains and names harvester for OSINT"
        },
        {
          "id": "https://asciiflow.com/",
          "author": null,
          "description": "Comments",
          "link": "https://asciiflow.com/",
          "publishedOn": "2021-06-17T04:58:50.000Z",
          "wordCount": 3,
          "title": "ASCIIFlow Diagram Tool"
        },
        {
          "id": "https://ankane.org/new-ml-gems",
          "author": null,
          "description": "Comments",
          "link": "https://ankane.org/new-ml-gems",
          "publishedOn": "2021-06-16T08:48:09.000Z",
          "wordCount": 1187,
          "title": "New Machine Learning Gems for Ruby"
        }
      ]
    }
  ],
  "cliVersion": "1.10.2"
}